{"_path":"/incomplete-playbooks/vendor-management","_dir":"incomplete-playbooks","_draft":false,"_partial":false,"_locale":"","_empty":false,"title":"Vendor Management","description":"","body":{"type":"root","children":[{"type":"element","tag":"h1","props":{"id":"vendor-management"},"children":[{"type":"text","value":"Vendor Management"}]},{"type":"element","tag":"alert","props":{"type":"info"},"children":[{"type":"element","tag":"p","props":{},"children":[{"type":"text","value":"This document describes the processes that support the following company policies:"}]},{"type":"element","tag":"ul","props":{},"children":[{"type":"element","tag":"li","props":{},"children":[{"type":"element","tag":"policy-links","props":{":drata-policy-id":"19","policy-name":"Vendor Management Policy","policy-slug":"vendor-maangement-policy"},"children":[]}]}]}]},{"type":"element","tag":"h2","props":{"id":"regular-reviews"},"children":[{"type":"text","value":"Regular Reviews"}]},{"type":"element","tag":"p","props":{},"children":[{"type":"text","value":"TODO: the policy does not state that regular reviews are needed, is it implied by another policy?"}]}],"toc":{"title":"","searchDepth":2,"depth":2,"links":[{"id":"regular-reviews","depth":2,"text":"Regular Reviews"}]}},"_type":"markdown","_id":"content:5.incomplete-playbooks:vendor-management.md","_source":"content","_file":"5.incomplete-playbooks/vendor-management.md","_extension":"md"}